README.rst
setup.py
Neu/NerModel.py
Neu/ParserModel.py
Neu/PosModel.py
Neu/SegModel.py
Neu/__init__.py
Neu/parameter.py
Neu/util.py
Neu.egg-info/PKG-INFO
Neu.egg-info/SOURCES.txt
Neu.egg-info/dependency_links.txt
Neu.egg-info/top_level.txt
Neu/model/__init__.py
Neu/model/ner.model
Neu/model/paras
Neu/model/seg.model
Neu/model/word_dict
Neu/nn/LSTM.py
Neu/nn/__init__.py
Neu/nn/ner.model
Neu/nn/op.py
Neu/nn/tensor.py
Neu/nn/test.txt