Metadata-Version: 1.1
Name: Neu
Version: 1.4
Summary: 中文自然语言处理工具包
Home-page: https://github.com/Woooooody/Neu
Author: UNKNOWN
Author-email: wujinhang0729@gmail.com
License: BSD License
Keywords: NLP,tokenizing,Chinese word segementation
Platform: UNKNOWN
Classifier: Development Status :: 3 - Alpha
Classifier: Operating System :: OS Independent
Classifier: Intended Audience :: Developers
Classifier: License :: OSI Approved :: BSD License
Classifier: Programming Language :: Python
Classifier: Programming Language :: Python :: Implementation
Classifier: Programming Language :: Python :: 3
Classifier: Programming Language :: Python :: 3.4
Classifier: Programming Language :: Python :: 3.5
Classifier: Programming Language :: Python :: 3.6
Classifier: Topic :: Software Development :: Libraries
